frappyapibilling/__init__.py
frappyapibilling/api_billing.py
frappyapibilling/quota_definitions.py
frappyapibilling/usage_store.py
frappyapibilling-0.1.0.dist-info/LICENSE
frappyapibilling-0.1.0.dist-info/METADATA
frappyapibilling-0.1.0.dist-info/WHEEL
frappyapibilling-0.1.0.dist-info/top_level.txt
frappyapibilling-0.1.0.dist-info/RECORD
