Metadata-Version: 2.1
Name: frappyapibilling
Version: 0.1.0
Summary: Billing and Quota Backend for Plan-Based, Restricted API Access
Home-page: https://github.com/ilfrich/frappy-api-billing
Author: Peter Ilfrich
Author-email: das-peter@gmx.de
License: UNKNOWN
Platform: UNKNOWN
Requires-Dist: flask
